<?xml version='1.0' encoding='utf-8'?>
<annotation><filename>000180.jpg</filename><size><width>2340</width><height>1080</height><depth>3</depth></size><object><name>with_mask</name><bndbox><xmin>474</xmin><ymin>91</ymin><xmax>835</xmax><ymax>534</ymax></bndbox></object><object><name>with_mask</name><bndbox><xmin>812</xmin><ymin>200</ymin><xmax>1016</xmax><ymax>508</ymax></bndbox></object><object><name>with_mask</name><bndbox><xmin>1027</xmin><ymin>170</ymin><xmax>1202</xmax><ymax>402</ymax></bndbox></object><object><name>with_mask</name><bndbox><xmin>1391</xmin><ymin>114</ymin><xmax>1612</xmax><ymax>395</ymax></bndbox></object><object><name>with_mask</name><bndbox><xmin>1884</xmin><ymin>161</ymin><xmax>1998</xmax><ymax>361</ymax></bndbox></object></annotation>