<?xml version='1.0' encoding='utf-8'?>
<annotation><filename>002566.jpg</filename>
	<size>
		<width>1024</width>
		<height>754</height>
		<depth>3</depth>
	</size>
	<object>
		<name>without_mask</name>
		<bndbox>
			<xmin>197</xmin>
			<ymin>59</ymin>
			<xmax>317</xmax>
			<ymax>226</ymax>
		</bndbox>
	</object>
	<object>
		<name>without_mask</name>
		<bndbox>
			<xmin>310</xmin>
			<ymin>150</ymin>
			<xmax>419</xmax>
			<ymax>297</ymax>
		</bndbox>
	</object>
	<object>
		<name>without_mask</name>
		<bndbox>
			<xmin>449</xmin>
			<ymin>112</ymin>
			<xmax>523</xmax>
			<ymax>256</ymax>
		</bndbox>
	</object>
	<object>
		<name>without_mask</name>
		<bndbox>
			<xmin>530</xmin>
			<ymin>179</ymin>
			<xmax>608</xmax>
			<ymax>296</ymax>
		</bndbox>
	</object>
	<object>
		<name>without_mask</name>
		<bndbox>
			<xmin>625</xmin>
			<ymin>134</ymin>
			<xmax>711</xmax>
			<ymax>270</ymax>
		</bndbox>
	</object>
</annotation>